nadex_cli-1.0.3.dist-info/licenses/LICENSE
nadex_dashboard/__init__.py
nadex_dashboard/__main__.py
nadex_dashboard/config.py
nadex_dashboard/frontend.py
nadex_dashboard/helpers.py
nadex_dashboard/main.py
nadex_dashboard/messages.py
nadex_dashboard/parsing.py
nadex_dashboard/websocket_manager.py
nadex_cli-1.0.3.dist-info/METADATA
nadex_cli-1.0.3.dist-info/WHEEL
nadex_cli-1.0.3.dist-info/entry_points.txt
nadex_cli-1.0.3.dist-info/top_level.txt
nadex_cli-1.0.3.dist-info/RECORD
